picamraw/__init__.py
picamraw/constants.py
picamraw/main.py
picamraw/main_test.py
picamraw/resolution.py
picamraw/resolution_test.py
picamraw-1.2.64.dist-info/LICENSE.md
picamraw-1.2.64.dist-info/METADATA
picamraw-1.2.64.dist-info/WHEEL
picamraw-1.2.64.dist-info/top_level.txt
picamraw-1.2.64.dist-info/RECORD
