Metadata-Version: 2.1
Name: picamraw
Version: 1.2.64
Summary: Library for extracting raw bayer data from a Raspberry Pi JPEG+RAW file
Home-page: https://www.github.com/osmosystems/picamraw
Author: Osmo Systems
Author-email: dev@osmobot.com
License: UNKNOWN
Keywords: Raspberrypi,camera,RAW,bayer
Platform: UNKNOWN
Classifier: Intended Audience :: Developers
Classifier: License :: OSI Approved :: BSD License
Classifier: Operating System :: OS Independent
Classifier: Programming Language :: Python :: 3.6
Classifier: Topic :: Scientific/Engineering
Classifier: Topic :: Multimedia :: Graphics :: Capture :: Digital Camera
Classifier: Topic :: Multimedia :: Graphics :: Graphics Conversion
Classifier: Topic :: Software Development :: Libraries :: Python Modules
Requires-Python: ~=3.5
Requires-Dist: numpy
